setup.py
huest/__init__.py
huest/hounsfield_estimate.py
huest.egg-info/PKG-INFO
huest.egg-info/SOURCES.txt
huest.egg-info/dependency_links.txt
huest.egg-info/requires.txt
huest.egg-info/top_level.txt