Metadata-Version: 1.0
Name: huest
Version: 0.1.0
Summary: HoUnsfield ESTimate
Home-page: https://github.com/adler-j/huest
Author: Jonas Adler
Author-email: jonasadl@kth.se
License: GPLv3+
Keywords: research development emission prototyping imaging tomography
Platform: UNKNOWN
